aioscgi/__init__.py
aioscgi/asyncio.py
aioscgi/container.py
aioscgi/http.py
aioscgi/lifespan.py
aioscgi/main.py
aioscgi/py.typed
aioscgi/tcp.py
aioscgi/types.py
aioscgi-2.3.1.dist-info/licenses/LICENSE
aioscgi-2.3.1.dist-info/METADATA
aioscgi-2.3.1.dist-info/WHEEL
aioscgi-2.3.1.dist-info/entry_points.txt
aioscgi-2.3.1.dist-info/top_level.txt
aioscgi-2.3.1.dist-info/RECORD
