Metadata-Version: 2.4
Name: aioscgi
Version: 2.3.1
Summary: An ASGI server that speaks SCGI.
Author: Christopher Head
Project-URL: Repository, https://gitlab.com/Hawk777/aioscgi
Classifier: Development Status :: 5 - Production/Stable
Classifier: Intended Audience :: Developers
Classifier: License :: OSI Approved :: GNU General Public License v3 (GPLv3)
Classifier: Operating System :: OS Independent
Classifier: Programming Language :: Python :: 3
Classifier: Topic :: Internet :: WWW/HTTP :: Dynamic Content :: CGI Tools/Libraries
Classifier: Topic :: Software Development :: Libraries :: Python Modules
Requires-Python: >=3.11
License-File: LICENSE
Requires-Dist: sioscgi<6.0,>=5.0
Dynamic: license-file
